KMap/GUI.py
KMap/GUI_CLI.py
KMap/Mapper.py
KMap/__init__.py
KMap/cli.py
KMap/day.gif
KMap/night.gif
KMap/off.gif
KMap/offdark.png
KMap/on.gif
KMap/ondark.png
KarnaughMap-1.1.2.dist-info/LICENSE
KarnaughMap-1.1.2.dist-info/METADATA
KarnaughMap-1.1.2.dist-info/WHEEL
KarnaughMap-1.1.2.dist-info/entry_points.txt
KarnaughMap-1.1.2.dist-info/top_level.txt
KarnaughMap-1.1.2.dist-info/RECORD
