Metadata-Version: 2.1
Name: KarnaughMap
Version: 1.1.2
Summary: Dependency-free library to create Karnaugh Map objects which can be solved and manipulated (GUI and CLI included)
Home-page: https://github.com/BizTecBritain/KarnaughMap
Author: Alexander Bisland
Author-email: biztecbritain@gmail.com
Project-URL: Bug Tracker, https://github.com/BizTecBritain/KarnaughMap/issues
Classifier: Programming Language :: Python :: 3
Classifier: License :: OSI Approved :: MIT License
Classifier: Operating System :: OS Independent
Requires-Python: >=3.8
License-File: LICENSE
